sengen/__init__.py
sengen/abstract_generator.py
sengen/attractor.py
sengen/custom_attractor.py
sengen/custom_equation.py
sengen/data_generator.py
sengen/stationary.py
sengen/utils.py
sengen-0.1.0.dist-info/LICENSE.md
sengen-0.1.0.dist-info/WHEEL
sengen-0.1.0.dist-info/METADATA
sengen-0.1.0.dist-info/RECORD
